fds/__init__.py
fds/sdk/__init__.py
fds/sdk/Symbology/__init__.py
fds/sdk/Symbology/api_client.py
fds/sdk/Symbology/configuration.py
fds/sdk/Symbology/exceptions.py
fds/sdk/Symbology/model_utils.py
fds/sdk/Symbology/rest.py
fds/sdk/Symbology/api/__init__.py
fds/sdk/Symbology/api/historical_identifier_resolution_api.py
fds/sdk/Symbology/api/identifier_resolution_api.py
fds/sdk/Symbology/apis/__init__.py
fds/sdk/Symbology/model/__init__.py
fds/sdk/Symbology/model/error_object.py
fds/sdk/Symbology/model/error_object_links.py
fds/sdk/Symbology/model/error_response.py
fds/sdk/Symbology/model/error_response_historical.py
fds/sdk/Symbology/model/error_response_sub_errors.py
fds/sdk/Symbology/model/get_historical_input_symbol_type.py
fds/sdk/Symbology/model/get_historical_output_symbol_types.py
fds/sdk/Symbology/model/get_ids_resolution.py
fds/sdk/Symbology/model/get_input_symbol_type.py
fds/sdk/Symbology/model/get_output_symbol_types.py
fds/sdk/Symbology/model/identifier_resolution.py
fds/sdk/Symbology/model/identifier_resolution_historical.py
fds/sdk/Symbology/model/identifier_resolution_historical_request.py
fds/sdk/Symbology/model/identifier_resolution_historical_request_body.py
fds/sdk/Symbology/model/identifier_resolution_historical_response.py
fds/sdk/Symbology/model/identifier_resolution_request.py
fds/sdk/Symbology/model/identifier_resolution_response.py
fds/sdk/Symbology/models/__init__.py
fds.sdk.Symbology-3.1.2.dist-info/LICENSE
fds.sdk.Symbology-3.1.2.dist-info/METADATA
fds.sdk.Symbology-3.1.2.dist-info/WHEEL
fds.sdk.Symbology-3.1.2.dist-info/top_level.txt
fds.sdk.Symbology-3.1.2.dist-info/RECORD
